EasyThreadings.py
EasyThreadings/More.py
EasyThreadings-1.0.1.dist-info/LICENSE
EasyThreadings-1.0.1.dist-info/METADATA
EasyThreadings-1.0.1.dist-info/WHEEL
EasyThreadings-1.0.1.dist-info/top_level.txt
EasyThreadings-1.0.1.dist-info/RECORD
