Metadata-Version: 2.1
Name: EasyThreadings
Version: 1.0.1
Summary: EasyThreadings · 一个专为简单线程而设计的模块
Home-page: UNKNOWN
Author: YunDuanModule
License: UNKNOWN
Keywords: Easy,Threading,EasyThreading,EasyThread,Thread
Platform: UNKNOWN
Classifier: Programming Language :: Python :: 3
Classifier: License :: OSI Approved :: MIT License
Classifier: Operating System :: OS Independent
Requires-Python: >=3.6
License-File: LICENSE
